{"chunk_definitions":[{"chunk_id":"csetup_chunk","chunk_label":"setup","document_id":"F367072A","expansion_state":0,"options":{"engine":"r","include":false,"label":"setup"},"row":53,"row_count":1,"visible":true},{"chunk_id":"c8nhpcwo0ku8a","chunk_label":"unnamed-chunk-1","document_id":"F367072A","expansion_state":0,"options":{"echo":false,"engine":"r","label":"unnamed-chunk-177"},"row":74,"row_count":1,"visible":true},{"chunk_id":"ccxc4yoy1tzdu","chunk_label":"unnamed-chunk-2","document_id":"F367072A","expansion_state":0,"options":{"echo":false,"engine":"r","label":"unnamed-chunk-178"},"row":153,"row_count":1,"visible":true},{"chunk_id":"c6fujws9bunpk","chunk_label":"unnamed-chunk-3","document_id":"F367072A","expansion_state":0,"options":{"echo":false,"engine":"r","label":"unnamed-chunk-179"},"row":158,"row_count":1,"visible":true},{"chunk_id":"cn56huoc7ai4j","chunk_label":"unnamed-chunk-4","document_id":"F367072A","expansion_state":0,"options":{"echo":false,"engine":"r","label":"unnamed-chunk-180"},"row":207,"row_count":1,"visible":true},{"chunk_id":"c445ji8jx5xzt","chunk_label":"unnamed-chunk-5","document_id":"F367072A","expansion_state":0,"options":{"echo":false,"engine":"r","label":"unnamed-chunk-181"},"row":246,"row_count":1,"visible":true},{"chunk_id":"ckfgwxk2n53ot","chunk_label":"unnamed-chunk-6","document_id":"F367072A","expansion_state":0,"options":{"engine":"r","label":"unnamed-chunk-205"},"row":344,"row_count":1,"visible":true},{"chunk_id":"caiobi9ilrk9d","chunk_label":"unnamed-chunk-7","document_id":"F367072A","expansion_state":0,"options":{"echo":false,"engine":"r","label":"unnamed-chunk-208"},"row":364,"row_count":1,"visible":true},{"chunk_id":"c29zqkd7cj4dd","chunk_label":"unnamed-chunk-8","document_id":"F367072A","expansion_state":0,"options":{"engine":"r","fig.height":4,"fig.width":6,"label":"unnamed-chunk-209"},"row":380,"row_count":1,"visible":true},{"chunk_id":"c5a4081iffdw3","chunk_label":"unnamed-chunk-9","document_id":"F367072A","expansion_state":0,"options":{"echo":false,"engine":"r","label":"unnamed-chunk-212"},"row":409,"row_count":1,"visible":true},{"chunk_id":"cbocj2mjq4ruk","chunk_label":"unnamed-chunk-10","document_id":"F367072A","expansion_state":0,"options":{"echo":false,"engine":"r","label":"unnamed-chunk-214"},"row":426,"row_count":1,"visible":true},{"chunk_id":"cq8nms90cmo4l","chunk_label":"unnamed-chunk-11","document_id":"F367072A","expansion_state":0,"options":{"engine":"r","label":"unnamed-chunk-215"},"row":495,"row_count":1,"visible":true},{"chunk_id":"clp2nm4emn1cm","chunk_label":"unnamed-chunk-12","document_id":"F367072A","expansion_state":0,"options":{"echo":false,"engine":"r","label":"unnamed-chunk-219"},"row":510,"row_count":1,"visible":true},{"chunk_id":"cqqqvgjrenfol","chunk_label":"unnamed-chunk-13","document_id":"F367072A","expansion_state":0,"options":{"echo":false,"engine":"r","label":"unnamed-chunk-218"},"row":527,"row_count":1,"visible":true},{"chunk_id":"c7i4vbwzhko2i","chunk_label":"unnamed-chunk-16","document_id":"F367072A","expansion_state":0,"options":{"echo":false,"engine":"r","label":"unnamed-chunk-229"},"row":912,"row_count":1,"visible":true},{"chunk_id":"cjlt26fw0pd7d","chunk_label":"unnamed-chunk-17","document_id":"F367072A","expansion_state":0,"options":{"echo":false,"engine":"r","label":"unnamed-chunk-234"},"row":948,"row_count":1,"visible":true},{"chunk_id":"co5o5x411t67p","chunk_label":"unnamed-chunk-18","document_id":"F367072A","expansion_state":0,"options":{"echo":false,"engine":"r","label":"unnamed-chunk-235"},"row":970,"row_count":1,"visible":true},{"chunk_id":"cn8rt3nhlnic7","chunk_label":"unnamed-chunk-19","document_id":"F367072A","expansion_state":0,"options":{"echo":false,"engine":"r","label":"unnamed-chunk-239"},"row":996,"row_count":1,"visible":true},{"chunk_id":"chqe6ko16t9b1","chunk_label":"unnamed-chunk-21","document_id":"F367072A","expansion_state":0,"options":{"echo":false,"engine":"r","label":"unnamed-chunk-243"},"row":1064,"row_count":1,"visible":true},{"chunk_id":"cjbeof6iao0ys","chunk_label":"unnamed-chunk-25","document_id":"F367072A","expansion_state":0,"options":{"echo":false,"engine":"r","label":"unnamed-chunk-245"},"row":1239,"row_count":1,"visible":true},{"chunk_id":"cwbzx3zoh1e6v","chunk_label":"unnamed-chunk-26","document_id":"F367072A","expansion_state":0,"options":{"echo":false,"engine":"r","label":"unnamed-chunk-256"},"row":1267,"row_count":1,"visible":true},{"chunk_id":"c5tffzkwerk1c","chunk_label":"unnamed-chunk-28","document_id":"F367072A","expansion_state":0,"options":{"engine":"r","label":"unnamed-chunk-13"},"row":1354,"row_count":1,"visible":true},{"chunk_id":"ced4mp49v6pp9","chunk_label":"unnamed-chunk-29","document_id":"F367072A","expansion_state":0,"options":{"engine":"r","label":"unnamed-chunk-21"},"row":1383,"row_count":1,"visible":true},{"chunk_id":"csoqcntbufewd","chunk_label":"unnamed-chunk-33","document_id":"F367072A","expansion_state":0,"options":{"echo":false,"engine":"r","label":"unnamed-chunk-25"},"row":1574,"row_count":1,"visible":true},{"chunk_id":"crwfe7orzg3qp","chunk_label":"unnamed-chunk-34","document_id":"F367072A","expansion_state":0,"options":{"engine":"r","label":"unnamed-chunk-29"},"row":1595,"row_count":1,"visible":true},{"chunk_id":"cm68m2497vetl","chunk_label":"unnamed-chunk-38","document_id":"F367072A","expansion_state":0,"options":{"echo":false,"engine":"r","label":"unnamed-chunk-31"},"row":1839,"row_count":1,"visible":true},{"chunk_id":"czxdccis8vplr","chunk_label":"unnamed-chunk-39","document_id":"F367072A","expansion_state":0,"options":{"echo":false,"engine":"r","label":"unnamed-chunk-32"},"row":1863,"row_count":1,"visible":true},{"chunk_id":"cuk9b80wgay02","chunk_label":"unnamed-chunk-40","document_id":"F367072A","expansion_state":0,"options":{"echo":false,"engine":"r","label":"unnamed-chunk-33"},"row":1908,"row_count":1,"visible":true}],"chunk_rendered_width":400,"default_chunk_options":{"cache":true,"echo":true,"error":false,"root_dir":"C:/Users/Will Koehrsen/Documents/DSCI 451/17f-dsci351-451-wjk68/1-assignments/SemProj-451/building_energy_eda/scripts","warning":false},"doc_write_time":1512915436,"working_dir":null}